LICENSE
MANIFEST.in
README.md
pyproject.toml
setup.cfg
setup.py
mquery.egg-info/PKG-INFO
mquery.egg-info/SOURCES.txt
mquery.egg-info/dependency_links.txt
mquery.egg-info/requires.txt
mquery.egg-info/top_level.txt
src/__init__.py
src/alembic.ini
src/app.py
src/config.py
src/daemon.py
src/db.py
src/metadata.py
src/schema.py
src/tasks.py
src/util.py
src/lib/__init__.py
src/lib/ursadb.py
src/lib/yaraparse.py
src/migrations/__init__.py
src/migrations/env.py
src/migrations/versions/6b495d5a4855_cascade_jobagent_match_and_del_removed_status_create_enum_jobstatus.py
src/migrations/versions/702d19cfa063_add_queuedfile.py
src/migrations/versions/cbbba858deb0_init.py
src/migrations/versions/dbb81bd4d47f_add_jobagent.py
src/migrations/versions/f623e1057b00_added_context_column_into_match_table.py
src/models/__init__.py
src/models/agentgroup.py
src/models/configentry.py
src/models/job.py
src/models/jobagent.py
src/models/match.py
src/models/queuedfile.py
src/mqueryfront/build/asset-manifest.json
src/mqueryfront/build/favicon.ico
src/mqueryfront/build/index.html
src/mqueryfront/build/manifest.json
src/mqueryfront/build/static/css/main.1ccaa94c.css
src/mqueryfront/build/static/css/main.1ccaa94c.css.map
src/mqueryfront/build/static/js/main.f971bfd1.js
src/mqueryfront/build/static/js/main.f971bfd1.js.LICENSE.txt
src/mqueryfront/build/static/js/main.f971bfd1.js.map
src/mqueryfront/build/static/media/codicon.b797181c93b3755f4fa1.ttf
src/mqueryfront/build/static/media/fontawesome-webfont.1e59d2330b4c6deb84b3.ttf
src/mqueryfront/build/static/media/fontawesome-webfont.20fd1704ea223900efa9.woff2
src/mqueryfront/build/static/media/fontawesome-webfont.8b43027f47b20503057d.eot
src/mqueryfront/build/static/media/fontawesome-webfont.c1e38fd9e0e74ba58f7a.svg
src/mqueryfront/build/static/media/fontawesome-webfont.f691f37e57f04c152e23.woff
src/mqueryfront/build/static/media/logo.b5c55d23c882fe844635a19a8c5ea3e7.svg
src/plugins/__init__.py
src/plugins/archive.py
src/plugins/blacklist.py
src/plugins/cuckoo_analysis.py
src/plugins/cuckoo_binaries.py
src/plugins/example_plugin.py
src/plugins/example_typed_config_plugin.py
