Metadata-Version: 2.1
Name: mquery
Version: 1.6.0
Summary: Blazingly fast Yara queries for malware analysts
Classifier: Programming Language :: Python
Classifier: Operating System :: OS Independent
License-File: LICENSE
Requires-Dist: alembic==1.11.1
Requires-Dist: annotated-types==0.7.0
Requires-Dist: anyio==4.6.0
Requires-Dist: asgiref==3.4.1
Requires-Dist: cachetools==5.5.0
Requires-Dist: certifi==2024.8.30
Requires-Dist: cffi==1.17.1
Requires-Dist: charset-normalizer==3.3.2
Requires-Dist: click==8.1.7
Requires-Dist: cryptography==43.0.1
Requires-Dist: Deprecated==1.2.13
Requires-Dist: fastapi==0.115.0
Requires-Dist: h11==0.14.0
Requires-Dist: idna==3.10
Requires-Dist: psycopg2==2.9.9
Requires-Dist: pycparser==2.22
Requires-Dist: pydantic==1.10.18
Requires-Dist: pydantic_core==2.23.4
Requires-Dist: PyJWT[crypto]==2.9.0
Requires-Dist: pyzmq==26.2.0
Requires-Dist: redis==5.0.8
Requires-Dist: requests==2.32.2
Requires-Dist: rq==1.16.2
Requires-Dist: sniffio==1.3.1
Requires-Dist: sqlmodel==0.0.11
Requires-Dist: starlette==0.38.6
Requires-Dist: typed-config==2.0.3
Requires-Dist: types-requests==2.32.0.20240914
Requires-Dist: typing_extensions==4.12.2
Requires-Dist: urllib3==2.2.3
Requires-Dist: uvicorn==0.30.6
Requires-Dist: wrapt==1.16.0
Requires-Dist: yara-python==4.5.1
Requires-Dist: yaramod==3.23.0
